odoo/addons/base_location_thailand/README.rst
odoo/addons/base_location_thailand/__init__.py
odoo/addons/base_location_thailand/__manifest__.py
odoo/addons/base_location_thailand/data/TH_en.txt
odoo/addons/base_location_thailand/data/TH_th.txt
odoo/addons/base_location_thailand/i18n/base_location_thailand.pot
odoo/addons/base_location_thailand/models/__init__.py
odoo/addons/base_location_thailand/models/res_company.py
odoo/addons/base_location_thailand/models/res_partner.py
odoo/addons/base_location_thailand/readme/CONTRIBUTORS.rst
odoo/addons/base_location_thailand/readme/CREDITS.rst
odoo/addons/base_location_thailand/readme/DESCRIPTION.rst
odoo/addons/base_location_thailand/readme/INSTALL.rst
odoo/addons/base_location_thailand/readme/USAGE.rst
odoo/addons/base_location_thailand/static/description/icon.png
odoo/addons/base_location_thailand/static/description/index.html
odoo/addons/base_location_thailand/wizard/__init__.py
odoo/addons/base_location_thailand/wizard/geonames_import.py
odoo/addons/base_location_thailand/wizard/geonames_import_view.xml
odoo13_addon_base_location_thailand-13.0.1.0.1.dev1.dist-info/METADATA
odoo13_addon_base_location_thailand-13.0.1.0.1.dev1.dist-info/WHEEL
odoo13_addon_base_location_thailand-13.0.1.0.1.dev1.dist-info/top_level.txt
odoo13_addon_base_location_thailand-13.0.1.0.1.dev1.dist-info/RECORD
